{
	"success":true,
	"data":[
		{
			"id":"1",
			"text":"Silky",
			"order":"10"
		},{
			"id":"2",
			"text":"dashed",
			"order":"5"
		},{
			"id":"3",
			"text":"rised",
			"order":"3"
		},{
			"id":"4",
			"text":"services",
			"order":"2"
		},{
			"id":"5",
			"text":"Absent",
			"order":"12"
		},{
			"id":"6",
			"text":"units",
			"order":"6"
		},{
			"id":"7",
			"text":"Absent_dd",
			"order":"4"
		},{
			"id":"8",
			"text":"terms",
			"order":"1"
		},{
			"id":"9",
			"text":"wait",
			"order":"11"
		},{
			"id":"10",
			"text":"query",
			"order":"7"
		},{
			"id":"11",
			"text":"bills",
			"order":"8"
		},{
			"id":"12",
			"text":"allowed",
			"order":"9"
		}
	]
}