{
  "success": true,
  "rows": [
     {
      "id":"1",
      "icon":"fa-eyedropper",
     "title":"期间核查的任务1",
      "subTitle":"任务分配",
      "total":"3",
      "state":"danger",
      "hrefStr":"/xx/xx",
      "parameter":{"b":1,"a":2}
    },{
      "id":"2",
      "icon":"fa-crosshairs",
      "title":"期间核查的任务2",
      "subTitle":"任务分配",
      "total":"5",
      "state":"warning",
      "hrefStr":"/xx/xx",
      "parameter":{"b":1,"a":2}
    },{
      "id":"3",
      "icon":"fa-check-square-o",
     "title":"期间核查的任务3",
      "subTitle":"任务分配",
      "total":"2",
      "state":"warning",
      "hrefStr":"/xx/xx",
      "parameter":{"b":1,"a":2}
    },{
      "id":"4",
      "icon":"fa-users",
      "title":"期间核查的任务4",
      "subTitle":"任务分配",
      "total":"1",
      "state":"info",
      "hrefStr":"/xx/xx",
      "parameter":{"b":1,"a":2}
    },{
      "id":"5",
      "icon":"fa-sliders",
     "title":"期间核查的任务5",
      "subTitle":"任务分配",
      "total":"3",
      "state":"danger",
      "hrefStr":"/xx/xx",
      "parameter":{"b":1,"a":2}
    },{
      "id":"6",
      "icon":"fa-eye",
     "title":"期间核查的任务6",
      "subTitle":"任务分配",
      "total":"3",
      "state":"danger",
      "hrefStr":"/xx/xx",
      "parameter":{"b":1,"a":2}
    },{
      "id":"7",
      "icon":"fa-eye",
     "title":"期间核查的任务7",
      "subTitle":"任务分配",
      "total":"3",
      "state":"danger",
      "hrefStr":"/xx/xx",
      "parameter":{"b":1,"a":2}
    },{
      "id":"8",
      "icon":"fa-crosshairs",
      "title":"期间核查的任务8",
      "subTitle":"任务分配",
      "total":"3",
      "state":"danger",
      "hrefStr":"/xx/xx",
      "parameter":{"b":1,"a":2}
    },{
      "id":"9",
      "icon":"fa-check-square-o",
      "title":"期间核查的任务9",
      "subTitle":"任务分配",
      "total":"3",
      "state":"danger",
      "hrefStr":"/xx/xx",
      "parameter":{"b":1,"a":2}
    },{
      "id":"10",
      "icon":"fa-users",
      "title":"期间核查的任务10",
      "subTitle":"任务分配",
      "total":"3",
      "state":"danger",
      "hrefStr":"/xx/xx",
      "parameter":{"b":1,"a":2}
    },{
      "id":"11",
      "icon":"fa-sliders",
      "title":"期间核查的任务11",
      "subTitle":"任务分配",
      "total":"3",
      "state":"danger",
      "hrefStr":"/xx/xx",
      "parameter":{"b":1,"a":2}
    },{
      "id":"12",
      "icon":"fa-eye",
      "title":"期间核查的任务12",
      "subTitle":"任务分配",
      "total":"3",
      "state":"danger",
      "hrefStr":"/xx/xx",
      "parameter":{"b":1,"a":2}
    },{
      "id":"13",
      "icon":"fa-eye",
      "title":"期间核查的任务13",
      "subTitle":"任务分配",
      "total":"3",
      "state":"danger",
      "hrefStr":"/xx/xx",
      "parameter":{"b":1,"a":2}
    }, {
      "id":"14",
      "icon":"fa-eyedropper",
      "title":"期间核查的任务14",
      "subTitle":"任务分配",
      "total":"3",
      "state":"danger",
      "hrefStr":"/xx/xx",
      "parameter":{"b":1,"a":2}
    },{
      "id":"15",
      "icon":"fa-crosshairs",
      "title":"期间核查的任务15",
      "subTitle":"任务分配",
      "total":"3",
      "state":"danger",
      "hrefStr":"/xx/xx",
      "parameter":{"b":1,"a":2}
    },{
      "id":"16",
      "icon":"fa-check-square-o",
      "title":"期间核查的任务16",
      "subTitle":"任务分配",
      "total":"3",
      "state":"danger",
      "hrefStr":"/xx/xx",
      "parameter":{"b":1,"a":2}
    },{
      "id":"17",
      "icon":"fa-users",
      "title":"期间核查的任务17",
      "subTitle":"任务分配",
      "total":"3",
      "state":"danger",
      "hrefStr":"/xx/xx",
      "parameter":{"b":1,"a":2}
    },{
      "id":"18",
      "icon":"fa-crosshairs",
      "title":"期间核查的任务18",
      "subTitle":"任务分配",
      "total":"3",
      "state":"danger",
      "hrefStr":"/xx/xx",
      "parameter":{"b":1,"a":2}
    },{
      "id":"19",
      "icon":"fa-check-square-o",
     "title":"期间核查的任务19",
      "subTitle":"任务分配",
      "total":"3",
      "state":"danger",
      "hrefStr":"/xx/xx",
      "parameter":{"b":1,"a":2}
    },{
      "id":"20",
      "icon":"fa-users",
      "title":"期间核查的任务20",
      "subTitle":"任务分配",
      "total":"3",
      "state":"danger",
      "hrefStr":"/xx/xx",
      "parameter":{"b":1,"a":2}
    },{
      "id":"21",
      "icon":"fa-sliders",
     "title":"期间核查的任务21",
      "subTitle":"任务分配",
      "total":"3",
      "state":"danger",
      "hrefStr":"/xx/xx",
      "parameter":{"b":1,"a":2}
    },{
      "id":"22",
      "icon":"fa-eye",
     "title":"期间核查的任务22",
      "subTitle":"任务分配",
      "total":"3",
      "state":"danger",
      "hrefStr":"/xx/xx",
      "parameter":{"b":1,"a":2}
    },{
      "id":"23",
      "icon":"fa-eye",
     "title":"期间核查的任务23",
      "subTitle":"任务分配",
      "total":"3",
      "state":"danger",
      "hrefStr":"/xx/xx",
      "parameter":{"b":1,"a":2}
    },{
      "id":"24",
      "icon":"fa-crosshairs",
      "title":"期间核查的任务24",
      "subTitle":"任务分配",
      "total":"3",
      "state":"danger",
      "hrefStr":"/xx/xx",
      "parameter":{"b":1,"a":2}
    },{
      "id":"25",
      "icon":"fa-check-square-o",
      "title":"期间核查的任务25",
      "subTitle":"任务分配",
      "total":"3",
      "state":"danger",
      "hrefStr":"/xx/xx",
      "parameter":{"b":1,"a":2}
    },{
      "id":"26",
      "icon":"fa-users",
      "title":"期间核查的任务26",
      "subTitle":"任务分配",
      "total":"3",
      "state":"danger",
      "hrefStr":"/xx/xx",
      "parameter":{"b":1,"a":2}
    },{
      "id":"27",
      "icon":"fa-sliders",
      "title":"期间核查的任务27",
      "subTitle":"任务分配",
      "total":"3",
      "state":"danger",
      "hrefStr":"/xx/xx",
      "parameter":{"b":1,"a":2}
    },{
      "id":"28",
      "icon":"fa-eye",
      "title":"期间核查的任务28",
      "subTitle":"任务分配",
      "total":"3",
      "state":"danger",
      "hrefStr":"/xx/xx",
      "parameter":{"b":1,"a":2}
    },{
      "id":"29",
      "icon":"fa-eye",
      "title":"期间核查的任务29",
      "subTitle":"任务分配",
      "total":"3",
      "state":"danger",
      "hrefStr":"/xx/xx",
      "parameter":{"b":1,"a":2}
    }, {
      "id":"30",
      "icon":"fa-eyedropper",
      "title":"期间核查的任务30",
      "subTitle":"任务分配",
      "total":"3",
      "state":"danger",
      "hrefStr":"/xx/xx",
      "parameter":{"b":1,"a":2}
    },{
      "id":"31",
      "icon":"fa-crosshairs",
      "title":"期间核查的任务31",
      "subTitle":"任务分配",
      "total":"3",
      "state":"danger",
      "hrefStr":"/xx/xx",
      "parameter":{"b":1,"a":2}
    },{
      "id":"32",
      "icon":"fa-check-square-o",
      "title":"期间核查的任务32",
      "subTitle":"任务分配",
      "total":"3",
      "state":"danger",
      "hrefStr":"/xx/xx",
      "parameter":{"b":1,"a":2}
    },{
      "id":"33",
      "icon":"fa-users",
      "title":"期间核查的任务33",
      "subTitle":"任务分配",
      "total":"3",
      "state":"danger",
      "hrefStr":"/xx/xx",
      "parameter":{"b":1,"a":2}
    },{
      "id":"34",
      "icon":"fa-eye",
      "title":"期间核查的任务34",
      "subTitle":"任务分配",
      "total":"3",
      "state":"danger",
      "hrefStr":"/xx/xx",
      "parameter":{"b":1,"a":2}
    }, {
      "id":"35",
      "icon":"fa-eyedropper",
      "title":"期间核查的任务35",
      "subTitle":"任务分配",
      "total":"3",
      "state":"danger",
      "hrefStr":"/xx/xx",
      "parameter":{"b":1,"a":2}
    },{
      "id":"36",
      "icon":"fa-crosshairs",
      "title":"期间核查的任务36",
      "subTitle":"任务分配",
      "total":"3",
      "state":"danger",
      "hrefStr":"/xx/xx",
      "parameter":{"b":1,"a":2}
    },{
      "id":"37",
      "icon":"fa-check-square-o",
      "title":"期间核查的任务37",
      "subTitle":"任务分配",
      "total":"3",
      "state":"danger",
      "hrefStr":"/xx/xx",
      "parameter":{"b":1,"a":2}
    },{
      "id":"38",
      "icon":"fa-users",
      "title":"期间核查的任务38",
      "subTitle":"任务分配",
      "total":"3",
      "state":"danger",
      "hrefStr":"/xx/xx",
      "parameter":{"b":1,"a":2}
    },{
      "id":"39",
      "icon":"fa-crosshairs",
      "title":"期间核查的任务39",
      "subTitle":"任务分配",
      "total":"5",
      "state":"warning",
      "hrefStr":"/xx/xx",
      "parameter":{"b":1,"a":2}
    },{
      "id":"40",
      "icon":"fa-check-square-o",
     "title":"期间核查的任务40",
      "subTitle":"任务分配",
      "total":"2",
      "state":"warning",
      "hrefStr":"/xx/xx",
      "parameter":{"b":1,"a":2}
    },{
      "id":"41",
      "icon":"fa-users",
      "title":"期间核查的任务41",
      "subTitle":"任务分配",
      "total":"1",
      "state":"info",
      "hrefStr":"/xx/xx",
      "parameter":{"b":1,"a":2}
    },{
      "id":"42",
      "icon":"fa-sliders",
     "title":"期间核查的任务42",
      "subTitle":"任务分配",
      "total":"3",
      "state":"danger",
      "hrefStr":"/xx/xx",
      "parameter":{"b":1,"a":2}
    },{
      "id":"43",
      "icon":"fa-eye",
     "title":"期间核查的任务43",
      "subTitle":"任务分配",
      "total":"3",
      "state":"danger",
      "hrefStr":"/xx/xx",
      "parameter":{"b":1,"a":2}
    },{
      "id":"44",
      "icon":"fa-eye",
     "title":"期间核查的任务44",
      "subTitle":"任务分配",
      "total":"3",
      "state":"danger",
      "hrefStr":"/xx/xx",
      "parameter":{"b":1,"a":2}
    },{
      "id":"45",
      "icon":"fa-crosshairs",
      "title":"期间核查的任务45",
      "subTitle":"任务分配",
      "total":"3",
      "state":"danger",
      "hrefStr":"/xx/xx",
      "parameter":{"b":1,"a":2}
    },{
      "id":"46",
      "icon":"fa-check-square-o",
      "title":"期间核查的任务46",
      "subTitle":"任务分配",
      "total":"3",
      "state":"danger",
      "hrefStr":"/xx/xx",
      "parameter":{"b":1,"a":2}
    },{
      "id":"47",
      "icon":"fa-users",
      "title":"期间核查的任务47",
      "subTitle":"任务分配",
      "total":"3",
      "state":"danger",
      "hrefStr":"/xx/xx",
      "parameter":{"b":1,"a":2}
    },{
      "id":"48",
      "icon":"fa-sliders",
      "title":"期间核查的任务48",
      "subTitle":"任务分配",
      "total":"3",
      "state":"danger",
      "hrefStr":"/xx/xx",
      "parameter":{"b":1,"a":2}
    },{
      "id":"49",
      "icon":"fa-eye",
      "title":"期间核查的任务49",
      "subTitle":"任务分配",
      "total":"3",
      "state":"danger",
      "hrefStr":"/xx/xx",
      "parameter":{"b":1,"a":2}
    },{
      "id":"50",
      "icon":"fa-eye",
      "title":"期间核查的任务50",
      "subTitle":"任务分配",
      "total":"3",
      "state":"danger",
      "hrefStr":"/xx/xx",
      "parameter":{"b":1,"a":2}
    }, {
      "id":"51",
      "icon":"fa-eyedropper",
      "title":"期间核查的任务51",
      "subTitle":"任务分配",
      "total":"3",
      "state":"danger",
      "hrefStr":"/xx/xx",
      "parameter":{"b":1,"a":2}
    },{
      "id":"52",
      "icon":"fa-crosshairs",
      "title":"期间核查的任务52",
      "subTitle":"任务分配",
      "total":"3",
      "state":"danger",
      "hrefStr":"/xx/xx",
      "parameter":{"b":1,"a":2}
    },{
      "id":"53",
      "icon":"fa-check-square-o",
      "title":"期间核查的任务53",
      "subTitle":"任务分配",
      "total":"3",
      "state":"danger",
      "hrefStr":"/xx/xx",
      "parameter":{"b":1,"a":2}
    },{
      "id":"54",
      "icon":"fa-users",
      "title":"期间核查的任务54",
      "subTitle":"任务分配",
      "total":"3",
      "state":"danger",
      "hrefStr":"/xx/xx",
      "parameter":{"b":1,"a":2}
    },{
      "id":"55",
      "icon":"fa-crosshairs",
      "title":"期间核查的任务55",
      "subTitle":"任务分配",
      "total":"3",
      "state":"danger",
      "hrefStr":"/xx/xx",
      "parameter":{"b":1,"a":2}
    },{
      "id":"56",
      "icon":"fa-check-square-o",
     "title":"期间核查的任务56",
      "subTitle":"任务分配",
      "total":"3",
      "state":"danger",
      "hrefStr":"/xx/xx",
      "parameter":{"b":1,"a":2}
    },{
      "id":"57",
      "icon":"fa-users",
      "title":"期间核查的任务57",
      "subTitle":"任务分配",
      "total":"3",
      "state":"danger",
      "hrefStr":"/xx/xx",
      "parameter":{"b":1,"a":2}
    },{
      "id":"58",
      "icon":"fa-sliders",
     "title":"期间核查的任务58",
      "subTitle":"任务分配",
      "total":"3",
      "state":"danger",
      "hrefStr":"/xx/xx",
      "parameter":{"b":1,"a":2}
    },{
      "id":"59",
      "icon":"fa-eye",
     "title":"期间核查的任务59",
      "subTitle":"任务分配",
      "total":"3",
      "state":"danger",
      "hrefStr":"/xx/xx",
      "parameter":{"b":1,"a":2}
    },{
      "id":"60",
      "icon":"fa-eye",
     "title":"期间核查的任务60",
      "subTitle":"任务分配",
      "total":"3",
      "state":"danger",
      "hrefStr":"/xx/xx",
      "parameter":{"b":1,"a":2}
    },{
      "id":"61",
      "icon":"fa-crosshairs",
      "title":"期间核查的任务61",
      "subTitle":"任务分配",
      "total":"3",
      "state":"danger",
      "hrefStr":"/xx/xx",
      "parameter":{"b":1,"a":2}
    },{
      "id":"62",
      "icon":"fa-check-square-o",
      "title":"期间核查的任务63",
      "subTitle":"任务分配",
      "total":"3",
      "state":"danger",
      "hrefStr":"/xx/xx",
      "parameter":{"b":1,"a":2}
    },{
      "id":"64",
      "icon":"fa-users",
      "title":"期间核查的任务64",
      "subTitle":"任务分配",
      "total":"3",
      "state":"danger",
      "hrefStr":"/xx/xx",
      "parameter":{"b":1,"a":2}
    },{
      "id":"65",
      "icon":"fa-sliders",
      "title":"期间核查的任务65",
      "subTitle":"任务分配",
      "total":"3",
      "state":"danger",
      "hrefStr":"/xx/xx",
      "parameter":{"b":1,"a":2}
    },{
      "id":"66",
      "icon":"fa-eye",
      "title":"期间核查的任务66",
      "subTitle":"任务分配",
      "total":"3",
      "state":"danger",
      "hrefStr":"/xx/xx",
      "parameter":{"b":1,"a":2}
    },{
      "id":"67",
      "icon":"fa-eye",
      "title":"期间核查的任务67",
      "subTitle":"任务分配",
      "total":"3",
      "state":"danger",
      "hrefStr":"/xx/xx",
      "parameter":{"b":1,"a":2}
    }, {
      "id":"68",
      "icon":"fa-eyedropper",
      "title":"期间核查的任务68",
      "subTitle":"任务分配",
      "total":"3",
      "state":"danger",
      "hrefStr":"/xx/xx",
      "parameter":{"b":1,"a":2}
    },{
      "id":"69",
      "icon":"fa-crosshairs",
      "title":"期间核查的任务69",
      "subTitle":"任务分配",
      "total":"3",
      "state":"danger",
      "hrefStr":"/xx/xx",
      "parameter":{"b":1,"a":2}
    },{
      "id":"70",
      "icon":"fa-check-square-o",
      "title":"期间核查的任务70",
      "subTitle":"任务分配",
      "total":"3",
      "state":"danger",
      "hrefStr":"/xx/xx",
      "parameter":{"b":1,"a":2}
    },{
      "id":"71",
      "icon":"fa-users",
      "title":"期间核查的任务71",
      "subTitle":"任务分配",
      "total":"3",
      "state":"danger",
      "hrefStr":"/xx/xx",
      "parameter":{"b":1,"a":2}
    },{
      "id":"72",
      "icon":"fa-eye",
      "title":"期间核查的任务72",
      "subTitle":"任务分配",
      "total":"3",
      "state":"danger",
      "hrefStr":"/xx/xx",
      "parameter":{"b":1,"a":2}
    }, {
      "id":"73",
      "icon":"fa-eyedropper",
      "title":"期间核查的任务73",
      "subTitle":"任务分配",
      "total":"3",
      "state":"danger",
      "hrefStr":"/xx/xx",
      "parameter":{"b":1,"a":2}
    },{
      "id":"74",
      "icon":"fa-crosshairs",
      "title":"期间核查的任务74",
      "subTitle":"任务分配",
      "total":"3",
      "state":"danger",
      "hrefStr":"/xx/xx",
      "parameter":{"b":1,"a":2}
    },{
      "id":"75",
      "icon":"fa-check-square-o",
      "title":"期间核查的任务75",
      "subTitle":"任务分配",
      "total":"3",
      "state":"danger",
      "hrefStr":"/xx/xx",
      "parameter":{"b":1,"a":2}
    },{
      "id":"76",
      "icon":"fa-users",
      "title":"期间核查的任务76",
      "subTitle":"任务分配",
      "total":"3",
      "state":"danger",
      "hrefStr":"/xx/xx",
      "parameter":{"b":1,"a":2}
    }
  ]
}