{
    "operator":{
        "defaultMode": {
            "chineseName": "类型",
            "validType": "string",
            "toolType": "select",
            "required":true,
            "default":"viewerdialog",
            "subdata": [{
                "value":"viewerdialog",
                "text":"viewerdialog"
            }],
            "help":""           
        },
        "text": {
            "chineseName": "按钮文字",
            "validType": "sting",
            "toolType": "text",
            "default": "",
            "help":"按钮中所显示的内容"
        },
        "title": {
            "chineseName": "标题",
            "validType": "string",
            "toolType": "text",
            "default": ""
        },
        "isReadonly": {
            "chineseName": "是否只读",
            "validType": "boolean",
            "toolType": "check",
            "default": false
        },
        "isHaveSaveAndAdd": {
            "chineseName": "是否保存并新增",
            "validType": "boolean",
            "toolType": "check",
            "default": true
        },
        "isKeepSelected": {
            "chineseName": "是否行选中",
            "validType": "boolean",
            "toolType": "check",
            "default":false,
            "help":""
        },
        "targetField": {
            "chineseName": "目标字段",
            "validType": "string",
            "toolType": "text",
            "default":"",
            "help":"目标字段 （keyField）"
        },
        "shortcutKey": {
            "chineseName": "快捷键",
            "validType": "string",
            "toolType": "text",
            "help":"举例:ctrl+e",
            "default":""
        },   
        "isInlineBtn": {
            "chineseName": "是否行内按钮",
            "validType": "boolean",
            "toolType": "check",
            "default":false        
        },
        "isMobileInlineBtn": {
            "chineseName": "是否手机行内按钮",
            "validType": "boolean",
            "toolType": "check",
            "default":true
        },
        "isMainDbAction": {
            "chineseName": "是否双击事件",
            "validType": "boolean",
            "toolType": "check",
            "default":"",
            "help":"是否将当前方法定义为表格行双击时执行的方法"    
        }
    },
    "data":{
        "ajax": {
            "chineseName": "ajax",
            "validType": "object",
            "toolType": "ajaxEditor",
            "required":true
        },
        "validateParams": {
            "chineseName": "参数验证公式",
            "validType": "object",
            "toolType": "textarea",
            "default":"",
            "help":"{'customerId':客户必填'},目前只支持是否存在的验证"         
        },
        
        "isSendPageParams": {
            "chineseName": "是否发送页面参数",
            "validType": "boolean",
            "toolType": "check",
            "default":true,
            "help":"参数发送时是否包含页面来源参数"
        },

        "isSetValueToSourcePage": {
            "chineseName": "是否对来源页面赋值",
            "validType": "boolean",
            "toolType": "check",
            "default":false,
            "help":"是否使用API返回的数据对来源页面赋值"
        },    
        "matrixVariable": {
            "chineseName": "矩阵传参",
            "validType": "object",
            "toolType": "textarea",
            "default":"",
            "help":"具体形式以API文档为主"         
        },
        "disabledExpression": {
            "chineseName": "禁用表达式",
            "validType": "object",
            "toolType": "textarea",
            "default":"",
            "help":"1:'disabled"
        },
        "parameterFormat": {
            "chineseName": "参数格式化",
            "validType": "object",
            "toolType": "textarea",
            "default":"",
            "help":"举例:{'id':'{sampleId}'}"         
        },
        "parameterFormatType": {
            "chineseName": "参数格式化类型",
            "validType": "string",
            "toolType": "textarea",
            "default":"add",
            "subdata":[
                {
                    "value":"cover",
                    "text":"覆盖"
                },
                {
                    "value":"add",
                    "text":"添加"
                }
            ],
            "help":"所定义的参数是否会覆盖默认参数"         
        }
        
    }
}